pyp4
