Metadata-Version: 2.1
Name: pyp4
Version: 0.13
Summary: api for perforce
Home-page: 
Author: niushuaibing
Author-email: niushuaibing@foxmail.com
Maintainer: niushuaibing
Maintainer-email: niushuaibing@foxmail.com
Platform: all
Classifier: Development Status :: 5 - Production/Stable
Classifier: Intended Audience :: Developers
Classifier: Programming Language :: Python :: 3
License-File: LICENSE
